zmp_alert_mcp_server/__init__.py
zmp_alert_mcp_server/__main__.py
zmp_alert_mcp_server/api_wrapper.py
zmp_alert_mcp_server/input_schema.py
zmp_alert_mcp_server/operations.py
zmp_alert_mcp_server/server.py
zmp_alert_mcp_server-0.1.9.dist-info/LICENSE
zmp_alert_mcp_server-0.1.9.dist-info/METADATA
zmp_alert_mcp_server-0.1.9.dist-info/WHEEL
zmp_alert_mcp_server-0.1.9.dist-info/entry_points.txt
zmp_alert_mcp_server-0.1.9.dist-info/RECORD
