Metadata-Version: 2.3
Name: zmp-alert-mcp-server
Version: 0.1.9
Summary: 
Author: Kilsoo Kang
Author-email: kilsoo75@gmail.com
Requires-Python: >=3.11,<4.0
Classifier: Programming Language :: Python :: 3
Classifier: Programming Language :: Python :: 3.11
Classifier: Programming Language :: Python :: 3.12
Classifier: Programming Language :: Python :: 3.13
Requires-Dist: mcp (>=1.4.1,<1.5)
Requires-Dist: zmp-openapi-models (>=0.1.1,<0.2.0)
